fs/azblob/__init__.py
fs/azblob/blob_file.py
fs/azblob/blob_fs.py
fs/azblob/blob_fs_v2.py
fs/azblob/const.py
fs/azblob/error_tools.py
fs/azblob/helpers.py
fs/opener/blob_fs.py
fs_azureblob-0.2.1.dist-info/LICENSE
fs_azureblob-0.2.1.dist-info/METADATA
fs_azureblob-0.2.1.dist-info/WHEEL
fs_azureblob-0.2.1.dist-info/entry_points.txt
fs_azureblob-0.2.1.dist-info/top_level.txt
fs_azureblob-0.2.1.dist-info/RECORD
