Metadata-Version: 2.1
Name: fs-azureblob
Version: 0.2.1
Summary: Azure blob storage filesystem for PyFilesystem2
Home-page: https://github.com/Breakthrough-Energy/fs-azureblob
Author: Breakthrough Energy
Author-email: sciences@breakthroughenergy.org
Project-URL: Bug Tracker, https://github.com/Breakthrough-Energy/fs-azureblob/issues
Classifier: License :: OSI Approved :: MIT License
Requires-Python: >=3.8
License-File: LICENSE
Requires-Dist: fs (~=2.4.13)
Requires-Dist: azure-storage-blob
Requires-Dist: azure-storage-file-datalake
